flexutils/__init__.py
flexutils/bibtex.py
flexutils/constants.py
flexutils/icon.png
flexutils/icon_square.png
flexutils/loading.gif
flexutils/protocols.conf
flexutils/utils.py
flexutils/protocols/__init__.py
flexutils/protocols/protocol_annotate_space.py
flexutils/protocols/protocol_associate_flex_space_to_particles.py
flexutils/protocols/protocol_auto_reference.py
flexutils/protocols/protocol_dimred.py
flexutils/protocols/protocol_filter_pca.py
flexutils/protocols/protocol_find_optimal_clusters.py
flexutils/protocols/protocol_order_volumes.py
flexutils/protocols/protocol_score_landscape.py
flexutils/protocols/protocol_select_views.py
flexutils/protocols/deprecated/__init__.py
flexutils/protocols/deprecated/custom_pdb_parser.py
flexutils/protocols/deprecated/protocol_angular_align_deep_nma.py
flexutils/protocols/deprecated/protocol_cluster_space.py
flexutils/protocols/deprecated/protocol_predict_deep_nma.py
flexutils/protocols/deprecated/annotation_2d_tools/__init__.py
flexutils/protocols/deprecated/annotation_2d_tools/viewer_interactive_2d.py
flexutils/protocols/deprecated/annotation_3d_tools/__init__.py
flexutils/protocols/deprecated/annotation_3d_tools/viewer_3d_pc.py
flexutils/protocols/deprecated/annotation_3d_tools/viewer_3d_slicer.py
flexutils/protocols/deprecated/annotation_3d_tools/viewer_interactive_2d_3d.py
flexutils/protocols/deprecated/chimera_viewers/__init__.py
flexutils/protocols/deprecated/chimera_viewers/viewer_morph_salesman_old.py
flexutils/protocols/deprecated/point_cloud_viewers/__init__.py
flexutils/protocols/deprecated/point_cloud_viewers/viewer_point_cloud.py
flexutils/protocols/deprecated/xmipp/__init__.py
flexutils/protocols/deprecated/xmipp/protocol_angular_align_deep_pose.py
flexutils/protocols/deprecated/xmipp/protocol_angular_align_homo_siren.py
flexutils/protocols/deprecated/xmipp/protocol_apply_field_nma.py
flexutils/protocols/deprecated/xmipp/protocol_predict_deep_pose.py
scipion_em_flexutils-3.4.0.dist-info/LICENSE
scipion_em_flexutils-3.4.0.dist-info/METADATA
scipion_em_flexutils-3.4.0.dist-info/WHEEL
scipion_em_flexutils-3.4.0.dist-info/entry_points.txt
scipion_em_flexutils-3.4.0.dist-info/top_level.txt
scipion_em_flexutils-3.4.0.dist-info/RECORD
