Metadata-Version: 2.1
Name: scipion-em-flexutils
Version: 3.4.0
Summary: Tools for 3D visualization and manipulation of flexibility data
Home-page: https://github.com/scipion-em/scipion-em-flexutils
Author: David Herreros
Author-email: dherreros@cnb.csic.es
Keywords: scipion continuous-heterogeneity imageprocessing scipion-3.0
License-File: LICENSE
Requires-Dist: scipion-em>=3.5.0
Requires-Dist: scipion-app>=3.3.1
Requires-Dist: scipion-pyworkflow>=3.7.0
Requires-Dist: h5py
Requires-Dist: xmipp-metadata<=1.2.0
Requires-Dist: scikit-image<=0.24.0,>=0.17.2
Requires-Dist: seaborn==0.12.2
Requires-Dist: scikit-learn>=1.2
Requires-Dist: pathos
Requires-Dist: gemmi
